cognito_jwt_verifier/__init__.py
cognito_jwt_verifier/verifier.py
cognito_jwt_verifier-0.0.4.dist-info/licenses/LICENSE
cognito_jwt_verifier-0.0.4.dist-info/METADATA
cognito_jwt_verifier-0.0.4.dist-info/WHEEL
cognito_jwt_verifier-0.0.4.dist-info/top_level.txt
cognito_jwt_verifier-0.0.4.dist-info/RECORD
