Metadata-Version: 2.4
Name: cognito-jwt-verifier
Version: 0.0.4
Summary: A utility for verifying JWTs issued by AWS Cognito.
Requires-Python: >=3.12
License-File: LICENSE
Requires-Dist: pytest==8.*
Requires-Dist: pytest-asyncio==1.*
Requires-Dist: aiohttp==3.*
Requires-Dist: pyjwt[crypto]==2.*
Dynamic: license-file
